{
  "items": [
    {
      "id": "media-delivery-preflight-suite-1",
      "title": "メディア納品前チェックスイート サンプル 1",
      "status": "ready",
      "filePath": "samples/product.png",
      "format": "png",
      "width": 1200,
      "height": 1200,
      "deliveryPreset": "BOOTH main image"
    },
    {
      "id": "media-delivery-preflight-suite-missing-required",
      "title": "必須項目不足サンプル",
      "status": "ready",
      "format": "png",
      "width": 1200,
      "height": 1200,
      "deliveryPreset": "BOOTH main image"
    }
  ]
}
